http_tarpit/__init__.py
http_tarpit/__main__.py
http_tarpit/constants.py
http_tarpit/server.py
http_tarpit/utils.py
http_tarpit-0.1.2.dist-info/LICENSE
http_tarpit-0.1.2.dist-info/METADATA
http_tarpit-0.1.2.dist-info/WHEEL
http_tarpit-0.1.2.dist-info/entry_points.txt
http_tarpit-0.1.2.dist-info/top_level.txt
http_tarpit-0.1.2.dist-info/zip-safe
http_tarpit-0.1.2.dist-info/RECORD
