Metadata-Version: 2.1
Name: http-tarpit
Version: 0.1.2
Summary: Web-server which produces infinite chunked-encoded responses
Home-page: https://github.com/Snawoot/http-tarpit
Author: Vladislav Yarmak
Author-email: vladislav-ex-src@vm-0.com
License: MIT
Platform: UNKNOWN
Classifier: Programming Language :: Python :: 3.5
Classifier: Programming Language :: Python :: 3.6
Classifier: Programming Language :: Python :: 3.7
Classifier: License :: OSI Approved :: MIT License
Classifier: Operating System :: OS Independent
Classifier: Development Status :: 4 - Beta
Classifier: Environment :: No Input/Output (Daemon)
Classifier: Intended Audience :: System Administrators
Classifier: Natural Language :: English
Classifier: Topic :: Internet
Classifier: Topic :: Security
Requires-Python: >=3.5.3
Requires-Dist: aiohttp (>=3.4.4)
